nesasm/__init__.py
nesasm/c6502.py
nesasm/cartridge.py
nesasm/compiler.py
nesasm/directives.py
nesasm/tests/__init__.py
nesasm/tests/adc_test.py
nesasm/tests/analyzer_test.py
nesasm/tests/and_test.py
nesasm/tests/asl_test.py
nesasm/tests/background_test.py
nesasm/tests/bcc_test.py
nesasm/tests/bcs_test.py
nesasm/tests/beq_test.py
nesasm/tests/bit_test.py
nesasm/tests/bmi_test.py
nesasm/tests/bne_test.py
nesasm/tests/bpl_test.py
nesasm/tests/bridge.py
nesasm/tests/bvc_test.py
nesasm/tests/bvs_test.py
nesasm/tests/cartridge_test.py
nesasm/tests/clc_test.py
nesasm/tests/cld_test.py
nesasm/tests/cli_test.py
nesasm/tests/clv_test.py
nesasm/tests/cmp_test.py
nesasm/tests/code_line_generator_test.py
nesasm/tests/commandline_test.py
nesasm/tests/compiler_test.py
nesasm/tests/constants_test.py
nesasm/tests/cpx_test.py
nesasm/tests/cpy_test.py
nesasm/tests/dec_test.py
nesasm/tests/dex_test.py
nesasm/tests/dey_test.py
nesasm/tests/directive_test.py
nesasm/tests/eor_test.py
nesasm/tests/guide_test.py
nesasm/tests/inc_test.py
nesasm/tests/inx_test.py
nesasm/tests/iny_test.py
nesasm/tests/jmp_test.py
nesasm/tests/jsr_test.py
nesasm/tests/label_test.py
nesasm/tests/lda_test.py
nesasm/tests/ldx_test.py
nesasm/tests/ldy_test.py
nesasm/tests/lowercase_test.py
nesasm/tests/lsr_test.py
nesasm/tests/movingsprite_test.py
nesasm/tests/nesasm_ci_test.py
nesasm/tests/nop_test.py
nesasm/tests/ora_test.py
nesasm/tests/pha_test.py
nesasm/tests/php_test.py
nesasm/tests/pla_test.py
nesasm/tests/plp_test.py
nesasm/tests/pynes_test.py
nesasm/tests/rol_test.py
nesasm/tests/ror_test.py
nesasm/tests/rti_test.py
nesasm/tests/rts_test.py
nesasm/tests/sbc_test.py
nesasm/tests/scrolling_test.py
nesasm/tests/sec_test.py
nesasm/tests/sed_test.py
nesasm/tests/sei_test.py
nesasm/tests/sta_test.py
nesasm/tests/stx_test.py
nesasm/tests/sty_test.py
nesasm/tests/tax_test.py
nesasm/tests/tay_test.py
nesasm/tests/tsx_test.py
nesasm/tests/txa_test.py
nesasm/tests/tya_test.py
nesasm-0.0.9.dist-info/LICENSE.txt
nesasm-0.0.9.dist-info/METADATA
nesasm-0.0.9.dist-info/WHEEL
nesasm-0.0.9.dist-info/RECORD
