Metadata-Version: 2.1
Name: nesasm
Version: 0.0.9
Summary: nesasm
Author: Guto Maia
Author-email: guto@guto.net
Requires-Python: >=3.11,<4.0
Classifier: Programming Language :: Python :: 3
Classifier: Programming Language :: Python :: 3.11
Classifier: Programming Language :: Python :: 3.12
Requires-Dist: lexical (>=0.0.5,<0.0.6)
